{
    "sourceFile": "v_makhadu/index.html",
    "activeCommit": 0,
    "commits": [
        {
            "activePatchIndex": 10,
            "patches": [
                {
                    "date": 1708447946810,
                    "content": "Index: \n===================================================================\n--- \n+++ \n"
                },
                {
                    "date": 1708447986814,
                    "content": "Index: \n===================================================================\n--- \n+++ \n@@ -5,9 +5,9 @@\n         <meta name=\"viewport\" content=\"width=device-width, initial-scale=1.0\" />\n         <!-- displays site properly based on user's device -->\n \n         <link rel=\"icon\" type=\"image/png\" sizes=\"32x32\" href=\"./images/favicon-32x32.png\" />\n-        <link rel=\"stylesheet\" href=\"./style.css\" />\n+        <link rel=\"stylesheet\" href=\"./styles.css\" />\n \n         <title>Frontend Mentor | Intro component with sign up form</title>\n     </head>\n     <body>\n"
                },
                {
                    "date": 1708448778342,
                    "content": "Index: \n===================================================================\n--- \n+++ \n@@ -24,9 +24,9 @@\n             </div>\n             <form action=\"#\" method=\"post\">\n                 <div>\n                     <input type=\"text\" name=\"firstName\" id=\"firstName\" placeholder=\"First Name\" autocomplete=\"off\" />\n-                    <img src=\"./images/icon-error.svg\" alt=\"\" aria-hidden=\"true\" id=\"alertInfo\" />\n+                    <img src=\"./images/icon-error.svg\" alt=\"\" aria-hidden=\"true\" class=\"alertInfo\" />\n                     <span class=\"alert\">First Name cannot be empty</span>\n                 </div>\n                 <div>\n                     <input type=\"text\" name=\"lastName\" id=\"lastName\" placeholder=\"Last Name\" autocomplete=\"off\" />\n"
                },
                {
                    "date": 1708448790903,
                    "content": "Index: \n===================================================================\n--- \n+++ \n@@ -29,9 +29,9 @@\n                     <span class=\"alert\">First Name cannot be empty</span>\n                 </div>\n                 <div>\n                     <input type=\"text\" name=\"lastName\" id=\"lastName\" placeholder=\"Last Name\" autocomplete=\"off\" />\n-                    <img src=\"./images/icon-error.svg\" alt=\"\" aria-hidden=\"true\" id=\"alertInfo\" />\n+                    <img src=\"./images/icon-error.svg\" alt=\"\" aria-hidden=\"true\" class=\"alertInfo\" />\n                     <span class=\"alert\">Last Name cannot be empty</span>\n                 </div>\n                 <div>\n                     <input type=\"text\" name=\"email\" id=\"email\" placeholder=\"Email Address\" autocomplete=\"off\" />\n"
                },
                {
                    "date": 1708448797398,
                    "content": "Index: \n===================================================================\n--- \n+++ \n@@ -34,9 +34,9 @@\n                     <span class=\"alert\">Last Name cannot be empty</span>\n                 </div>\n                 <div>\n                     <input type=\"text\" name=\"email\" id=\"email\" placeholder=\"Email Address\" autocomplete=\"off\" />\n-                    <img src=\"./images/icon-error.svg\" alt=\"\" aria-hidden=\"true\" id=\"alertInfo\" />\n+                    <img src=\"./images/icon-error.svg\" alt=\"\" aria-hidden=\"true\" class=\"alertInfo\" />\n                     <span class=\"alert\">Email Address cannot be empty</span>\n                 </div>\n                 <div>\n                     <input type=\"password\" name=\"password\" id=\"password\" placeholder=\"Password\" autocomplete=\"off\" />\n"
                },
                {
                    "date": 1708448804298,
                    "content": "Index: \n===================================================================\n--- \n+++ \n@@ -39,9 +39,9 @@\n                     <span class=\"alert\">Email Address cannot be empty</span>\n                 </div>\n                 <div>\n                     <input type=\"password\" name=\"password\" id=\"password\" placeholder=\"Password\" autocomplete=\"off\" />\n-                    <img src=\"./images/icon-error.svg\" alt=\"\" aria-hidden=\"true\" id=\"alertInfo\" />\n+                    <img src=\"./images/icon-error.svg\" alt=\"\" aria-hidden=\"true\" class=\"alertInfo\" />\n                     <span class=\"alert\">Password cannot be empty</span>\n                 </div>\n                 <button type=\"submit\">Claim your free trial</button>\n                 <div class=\"terms\">\n"
                },
                {
                    "date": 1708448823779,
                    "content": "Index: \n===================================================================\n--- \n+++ \n@@ -24,24 +24,24 @@\n             </div>\n             <form action=\"#\" method=\"post\">\n                 <div>\n                     <input type=\"text\" name=\"firstName\" id=\"firstName\" placeholder=\"First Name\" autocomplete=\"off\" />\n-                    <img src=\"./images/icon-error.svg\" alt=\"\" aria-hidden=\"true\" class=\"alertInfo\" />\n+                    <img src=\"./images/icon-error.svg\" alt=\"\" aria-hidden=\"true\" id=\"alertInfo\" />\n                     <span class=\"alert\">First Name cannot be empty</span>\n                 </div>\n                 <div>\n                     <input type=\"text\" name=\"lastName\" id=\"lastName\" placeholder=\"Last Name\" autocomplete=\"off\" />\n-                    <img src=\"./images/icon-error.svg\" alt=\"\" aria-hidden=\"true\" class=\"alertInfo\" />\n+                    <img src=\"./images/icon-error.svg\" alt=\"\" aria-hidden=\"true\" id=\"alertInfo\" />\n                     <span class=\"alert\">Last Name cannot be empty</span>\n                 </div>\n                 <div>\n                     <input type=\"text\" name=\"email\" id=\"email\" placeholder=\"Email Address\" autocomplete=\"off\" />\n-                    <img src=\"./images/icon-error.svg\" alt=\"\" aria-hidden=\"true\" class=\"alertInfo\" />\n+                    <img src=\"./images/icon-error.svg\" alt=\"\" aria-hidden=\"true\" id=\"alertInfo\" />\n                     <span class=\"alert\">Email Address cannot be empty</span>\n                 </div>\n                 <div>\n                     <input type=\"password\" name=\"password\" id=\"password\" placeholder=\"Password\" autocomplete=\"off\" />\n-                    <img src=\"./images/icon-error.svg\" alt=\"\" aria-hidden=\"true\" class=\"alertInfo\" />\n+                    <img src=\"./images/icon-error.svg\" alt=\"\" aria-hidden=\"true\" id=\"alertInfo\" />\n                     <span class=\"alert\">Password cannot be empty</span>\n                 </div>\n                 <button type=\"submit\">Claim your free trial</button>\n                 <div class=\"terms\">\n"
                },
                {
                    "date": 1708451108131,
                    "content": "Index: \n===================================================================\n--- \n+++ \n@@ -50,13 +50,17 @@\n             </form>\n         </main>\n \n         <footer>\n-            <p class=\"attribution\">\n+            <div class=\"attribution\">\n                 Challenge by\n-                <a href=\"https://www.frontendmentor.io?ref=challenge\" target=\"_blank\" rel=\"noopener\">Frontend Mentor</a>. Coded by\n-                <a href=\"#\">Your Name Here</a>.\n-            </p>\n+                <a\n+                    href=\"https://www.frontendmentor.io/challenges/intro-component-with-signup-form-5cf91bd49edda32581d28fd1/hub\"\n+                    target=\"_blank\"\n+                    rel=\"noopener noreferer\"\n+                    >Frontend Mentor</a\n+                >. Coded by <a href=\"https://github.com/cipdanila\" target=\"_blank\" rel=\"noopener noreferer\">Ciprian Danila</a>.\n+            </div>\n         </footer>\n         <script src=\"./script.js\"></script>\n     </body>\n </html>\n"
                },
                {
                    "date": 1708451157676,
                    "content": "Index: \n===================================================================\n--- \n+++ \n@@ -5,9 +5,9 @@\n         <meta name=\"viewport\" content=\"width=device-width, initial-scale=1.0\" />\n         <!-- displays site properly based on user's device -->\n \n         <link rel=\"icon\" type=\"image/png\" sizes=\"32x32\" href=\"./images/favicon-32x32.png\" />\n-        <link rel=\"stylesheet\" href=\"./styles.css\" />\n+        <link rel=\"stylesheet\" href=\"./style.css\" />\n \n         <title>Frontend Mentor | Intro component with sign up form</title>\n     </head>\n     <body>\n@@ -50,17 +50,13 @@\n             </form>\n         </main>\n \n         <footer>\n-            <div class=\"attribution\">\n+            <p class=\"attribution\">\n                 Challenge by\n-                <a\n-                    href=\"https://www.frontendmentor.io/challenges/intro-component-with-signup-form-5cf91bd49edda32581d28fd1/hub\"\n-                    target=\"_blank\"\n-                    rel=\"noopener noreferer\"\n-                    >Frontend Mentor</a\n-                >. Coded by <a href=\"https://github.com/cipdanila\" target=\"_blank\" rel=\"noopener noreferer\">Ciprian Danila</a>.\n-            </div>\n+                <a href=\"https://www.frontendmentor.io?ref=challenge\" target=\"_blank\" rel=\"noopener\">Frontend Mentor</a>. Coded by\n+                <a href=\"#\">Your Name Here</a>.\n+            </p>\n         </footer>\n         <script src=\"./script.js\"></script>\n     </body>\n </html>\n"
                },
                {
                    "date": 1708451338978,
                    "content": "Index: \n===================================================================\n--- \n+++ \n@@ -5,9 +5,9 @@\n         <meta name=\"viewport\" content=\"width=device-width, initial-scale=1.0\" />\n         <!-- displays site properly based on user's device -->\n \n         <link rel=\"icon\" type=\"image/png\" sizes=\"32x32\" href=\"./images/favicon-32x32.png\" />\n-        <link rel=\"stylesheet\" href=\"./style.css\" />\n+        <link rel=\"stylesheet\" href=\"./styles.css\" />\n \n         <title>Frontend Mentor | Intro component with sign up form</title>\n     </head>\n     <body>\n@@ -52,10 +52,14 @@\n \n         <footer>\n             <p class=\"attribution\">\n                 Challenge by\n-                <a href=\"https://www.frontendmentor.io?ref=challenge\" target=\"_blank\" rel=\"noopener\">Frontend Mentor</a>. Coded by\n-                <a href=\"#\">Your Name Here</a>.\n+                <a\n+                    href=\"https://www.frontendmentor.io/challenges/intro-component-with-signup-form-5cf91bd49edda32581d28fd1/hub\"\n+                    target=\"_blank\"\n+                    rel=\"noopener noreferer\"\n+                    >Frontend Mentor</a\n+                >. Coded by <a href=\"https://github.com/cipdanila\" target=\"_blank\" rel=\"noopener noreferer\">Ciprian Danila</a>.\n             </p>\n         </footer>\n         <script src=\"./script.js\"></script>\n     </body>\n"
                },
                {
                    "date": 1708452722883,
                    "content": "Index: \n===================================================================\n--- \n+++ \n@@ -49,9 +49,9 @@\n                 </div>\n             </form>\n         </main>\n \n-        <footer>\n+        <!-- <footer>\n             <p class=\"attribution\">\n                 Challenge by\n                 <a\n                     href=\"https://www.frontendmentor.io/challenges/intro-component-with-signup-form-5cf91bd49edda32581d28fd1/hub\"\n@@ -59,8 +59,8 @@\n                     rel=\"noopener noreferer\"\n                     >Frontend Mentor</a\n                 >. Coded by <a href=\"https://github.com/cipdanila\" target=\"_blank\" rel=\"noopener noreferer\">Ciprian Danila</a>.\n             </p>\n-        </footer>\n+        </footer> -->\n         <script src=\"./script.js\"></script>\n     </body>\n </html>\n"
                }
            ],
            "date": 1708447946810,
            "name": "Commit-0",
            "content": "<!DOCTYPE html>\n<html lang=\"en\">\n    <head>\n        <meta charset=\"UTF-8\" />\n        <meta name=\"viewport\" content=\"width=device-width, initial-scale=1.0\" />\n        <!-- displays site properly based on user's device -->\n\n        <link rel=\"icon\" type=\"image/png\" sizes=\"32x32\" href=\"./images/favicon-32x32.png\" />\n        <link rel=\"stylesheet\" href=\"./style.css\" />\n\n        <title>Frontend Mentor | Intro component with sign up form</title>\n    </head>\n    <body>\n        <header>\n            <h1>Learn to code by watching others</h1>\n            <p>\n                See how experienced developers solve problems in real-time. Watching scripted tutorials is great, but\n                understanding how developers think is invaluable.\n            </p>\n        </header>\n        <main>\n            <div class=\"info\">\n                <span><b>Try it free 7 days</b> then $20/mo. thereafter</span>\n            </div>\n            <form action=\"#\" method=\"post\">\n                <div>\n                    <input type=\"text\" name=\"firstName\" id=\"firstName\" placeholder=\"First Name\" autocomplete=\"off\" />\n                    <img src=\"./images/icon-error.svg\" alt=\"\" aria-hidden=\"true\" id=\"alertInfo\" />\n                    <span class=\"alert\">First Name cannot be empty</span>\n                </div>\n                <div>\n                    <input type=\"text\" name=\"lastName\" id=\"lastName\" placeholder=\"Last Name\" autocomplete=\"off\" />\n                    <img src=\"./images/icon-error.svg\" alt=\"\" aria-hidden=\"true\" id=\"alertInfo\" />\n                    <span class=\"alert\">Last Name cannot be empty</span>\n                </div>\n                <div>\n                    <input type=\"text\" name=\"email\" id=\"email\" placeholder=\"Email Address\" autocomplete=\"off\" />\n                    <img src=\"./images/icon-error.svg\" alt=\"\" aria-hidden=\"true\" id=\"alertInfo\" />\n                    <span class=\"alert\">Email Address cannot be empty</span>\n                </div>\n                <div>\n                    <input type=\"password\" name=\"password\" id=\"password\" placeholder=\"Password\" autocomplete=\"off\" />\n                    <img src=\"./images/icon-error.svg\" alt=\"\" aria-hidden=\"true\" id=\"alertInfo\" />\n                    <span class=\"alert\">Password cannot be empty</span>\n                </div>\n                <button type=\"submit\">Claim your free trial</button>\n                <div class=\"terms\">\n                    <span>By clicking the button, you are agreeing to our <b>Terms and Services</b></span>\n                </div>\n            </form>\n        </main>\n\n        <footer>\n            <p class=\"attribution\">\n                Challenge by\n                <a href=\"https://www.frontendmentor.io?ref=challenge\" target=\"_blank\" rel=\"noopener\">Frontend Mentor</a>. Coded by\n                <a href=\"#\">Your Name Here</a>.\n            </p>\n        </footer>\n        <script src=\"./script.js\"></script>\n    </body>\n</html>\n"
        }
    ]
}